LICENSE
MANIFEST.in
README.rst
setup.py
common/__init__.py
common/context_processors.py
common/fields.py
common/mail.py
common/models.py
common/tests.py
common/urls.py
common/util.py
common/views.py
common/static/bootstrap/css/bootstrap-responsive.css
common/static/bootstrap/css/bootstrap-responsive.min.css
common/static/bootstrap/css/bootstrap.css
common/static/bootstrap/css/bootstrap.min.css
common/static/bootstrap/img/glyphicons-halflings-white.png
common/static/bootstrap/img/glyphicons-halflings.png
common/static/bootstrap/js/bootstrap.js
common/static/bootstrap/js/bootstrap.min.js
common/static/css/style.css
common/static/images/glyphicons-halflings-white.png
common/static/images/glyphicons-halflings.png
common/static/images/sample.png
common/static/js/.jshintrc
common/static/js/core.js
common/static/js/jquery.common.js
common/static/js/jquery.common.js~
common/static/js/jquery.min.js
common/templates/404.html
common/templates/500.html
common/templates/flash_view.html
common/templates/form.confirm.html
common/templates/inc.content.html
common/templates/inc.flash.html
common/templates/inc.topbar.html
common/templates/page.confirm.html
common/templates/page.example.html
common/templates/page.form.html
common/templates/base/atom.xml
common/templates/base/layout.html
common/templates/base/rss.xml
common/templates/base/small.html
common/templates/email/email_base.html
common/templates/email/email_base.txt
common/templates/email/email_base_notification.html
common/templates/email/email_base_notification.txt
common/templates/forms/errors.html
common/templates/forms/fields.html
common/templates/forms/form.html
common/templates/pagination/basic.html
common/templatetags/__init__.py
common/templatetags/base.py
common/templatetags/humanize.py
common/templatetags/json.py
zero_common.egg-info/PKG-INFO
zero_common.egg-info/SOURCES.txt
zero_common.egg-info/dependency_links.txt
zero_common.egg-info/requires.txt
zero_common.egg-info/top_level.txt