Metadata-Version: 1.0
Name: zero-common
Version: 0.1.10
Summary: App with common views, libs and templates that can be used by other apps
Home-page: http://github.com/mandlaweb/Zero-Common
Author: Jose Maria Zambrana Arze
Author-email: contact@josezambrana.com
License: apache license v2.0
Keywords: zero common app
Platform: UNKNOWN
